fint_rtc_server/__init__.py
fint_rtc_server/config.py
fint_rtc_server/exceptions.py
fint_rtc_server/logger.py
fint_rtc_server/routes.py
fint_rtc_server/auth/__init__.py
fint_rtc_server/auth/noauth.py
fint_rtc_server/base/__init__.py
fint_rtc_server/base/multiuser.py
fint_rtc_server/base/session.py
fint_rtc_server/base/singleton.py
fint_rtc_server/base/websocket_handler.py
fint_rtc_server/base/ystore.py
fint_rtc_server/contents/__init__.py
fint_rtc_server/contents/utils.py
fint_rtc_server/model/__init__.py
fint_rtc_server/model/contents.py
fint_rtc_server/model/user.py
fint_rtc_server/multiuser/__init__.py
fint_rtc_server/multiuser/manager.py
fint_rtc_server/session/__init__.py
fint_rtc_server/session/websocket_manager.py
fint_rtc_server/session/websocket/__init__.py
fint_rtc_server/session/websocket/adapter.py
fint_rtc_server/session/websocket/handler.py
fint_rtc_server/session/websocket/utils.py
fint_rtc_server/ydoc/__init__.py
fint_rtc_server/ydoc/yfile.py
fint_rtc_server/ydoc/ynotebok.py
fint_rtc_server/ystore/__init__.py
fint_rtc_server/ystore/manager.py
fint_rtc_server-0.0.1.dist-info/METADATA
fint_rtc_server-0.0.1.dist-info/WHEEL
fint_rtc_server-0.0.1.dist-info/entry_points.txt
fint_rtc_server-0.0.1.dist-info/RECORD
