Metadata-Version: 2.1
Name: fint_rtc_server
Version: 0.0.1
Summary: An FPS plugin for the Yjs API, support multiuser and using ino for YRoom
Author-email: Wh1isper <9573586@qq.com>
License: BSD 3-Clause License
Keywords: fastapi,jupyter,pluggy,plugins,server
Requires-Python: >=3.7
Requires-Dist: fps-uvicorn
Requires-Dist: fps>=0.0.8
Requires-Dist: jupyter-ydoc
Requires-Dist: watchfiles<1,>=0.16.1
Requires-Dist: ypy-websocket
Provides-Extra: test
Requires-Dist: ipykernel; extra == 'test'
Requires-Dist: mypy; extra == 'test'
Requires-Dist: pytest; extra == 'test'
Requires-Dist: pytest-asyncio; extra == 'test'
Requires-Dist: pytest-env; extra == 'test'
Requires-Dist: requests; extra == 'test'
Requires-Dist: types-setuptools; extra == 'test'
Requires-Dist: websockets; extra == 'test'
